[{"mSpeed":0,"mCalorie":0,"mDistance":0,"mWalkStepCount":0,"mNowHealthyStep":0,"mTotalActiveTime":0,"mTimeUnit":600000,"mStepCount":0,"mRunStepCount":0,"mStartTime":0},{"mSpeed":0,"mCalorie":0,"mDistance":0,"mWalkStepCount":0,"mNowHealthyStep":0,"mTotalActiveTime":0,"mTimeUnit":600000,"mStepCount":0,"mRunStepCount":0,"mStartTime":0},{"mSpeed":0,"mCalorie":0,"mDistance":0,"mWalkStepCount":0,"mNowHealthyStep":0,"mTotalActiveTime":0,"mTimeUnit":600000,"mStepCount":0,"mRunStepCount":0,"mStartTime":0},{"mSpeed":0,"mCalorie":0,"mDistance":0,"mWalkStepCount":0,"mNowHealthyStep":0,"mTotalActiveTime":0,"mTimeUnit":600000,"mStepCount":0,"mRunStepCount":0,"mStartTime":0},{"mSpeed":0,"mCalorie":0,"mDistance":0,"mWalkStepCount":0,"mNowHealthyStep":0,"mTotalActiveTime":0,"mTimeUnit":600000,"mStepCount":0,"mRunStepCount":0,"mStartTime":0},{"mSpeed":0,"mCalorie":0,"mDistance":0,"mWalkStepCount":0,"mNowHealthyStep":0,"mTotalActiveTime":0,"mTimeUnit":600000,"mStepCount":0,"mRunStepCount":0,"mStartTime":0},{"mSpeed":0,"mCalorie":0,"mDistance":0,"mWalkStepCount":0,"mNowHealthyStep":0,"mTotalActiveTime":0,"mTimeUnit":600000,"mStepCount":0,"mRunStepCount":0,"mStartTime":0},{"mSpeed":0,"mCalorie":0,"mDistance":0,"mWalkStepCount":0,"mNowHealthyStep":0,"mTotalActiveTime":0,"mTimeUnit":600000,"mStepCount":0,"mRunStepCount":0,"mStartTime":0},{"mSpeed":0,"mCalorie":0,"mDistance":0,"mWalkStepCount":0,"mNowHealthyStep":0,"mTotalActiveTime":0,"mTimeUnit":600000,"mStepCount":0,"mRunStepCount":0,"mStartTime":0},{"mSpeed":0,"mCalorie":0,"mDistance":0,"mWalkStepCount":0,"mNowHealthyStep":0,"mTotalActiveTime":0,"mTimeUnit":600000,"mStepCount":0,"mRunStepCount":0,"mStartTime":0},{"mSpeed":0,"mCalorie":0,"mDistance":0,"mWalkStepCount":0,"mNowHealthyStep":0,"mTotalActiveTime":0,"mTimeUnit":600000,"mStepCount":0,"mRunStepCount":0,"mStartTime":0},{"mSpeed":0,"mCalorie":0,"mDistance":0,"mWalkStepCount":0,"mNowHealthyStep":0,"mTotalActiveTime":0,"mTimeUnit":600000,"mStepCount":0,"mRunStepCount":0,"mStartTime":0},{"mSpeed":0,"mCalorie":0,"mDistance":0,"mWalkStepCount":0,"mNowHealthyStep":0,"mTotalActiveTime":0,"mTimeUnit":600000,"mStepCount":0,"mRunStepCount":0,"mStartTime":0},{"mSpeed":0,"mCalorie":0,"mDistance":0,"mWalkStepCount":0,"mNowHealthyStep":0,"mTotalActiveTime":0,"mTimeUnit":600000,"mStepCount":0,"mRunStepCount":0,"mStartTime":0},{"mSpeed":0,"mCalorie":0,"mDistance":0,"mWalkStepCount":0,"mNowHealthyStep":0,"mTotalActiveTime":0,"mTimeUnit":600000,"mStepCount":0,"mRunStepCount":0,"mStartTime":0},{"mSpeed":0,"mCalorie":0,"mDistance":0,"mWalkStepCount":0,"mNowHealthyStep":0,"mTotalActiveTime":0,"mTimeUnit":600000,"mStepCount":0,"mRunStepCount":0,"mStartTime":0},{"mSpeed":0,"mCalorie":0,"mDistance":0,"mWalkStepCount":0,"mNowHealthyStep":0,"mTotalActiveTime":0,"mTimeUnit":600000,"mStepCount":0,"mRunStepCount":0,"mStartTime":0},{"mSpeed":0,"mCalorie":0,"mDistance":0,"mWalkStepCount":0,"mNowHealthyStep":0,"mTotalActiveTime":0,"mTimeUnit":600000,"mStepCount":0,"mRunStepCount":0,"mStartTime":0},{"mSpeed":0,"mCalorie":0,"mDistance":0,"mWalkStepCount":0,"mNowHealthyStep":0,"mTotalActiveTime":0,"mTimeUnit":600000,"mStepCount":0,"mRunStepCount":0,"mStartTime":0},{"mSpeed":0,"mCalorie":0,"mDistance":0,"mWalkStepCount":0,"mNowHealthyStep":0,"mTotalActiveTime":0,"mTimeUnit":600000,"mStepCount":0,"mRunStepCount":0,"mStartTime":0},{"mSpeed":0,"mCalorie":0,"mDistance":0,"mWalkStepCount":0,"mNowHealthyStep":0,"mTotalActiveTime":0,"mTimeUnit":600000,"mStepCount":0,"mRunStepCount":0,"mStartTime":0},{"mSpeed":0,"mCalorie":0,"mDistance":0,"mWalkStepCount":0,"mNowHealthyStep":0,"mTotalActiveTime":0,"mTimeUnit":600000,"mStepCount":0,"mRunStepCount":0,"mStartTime":0},{"mSpeed":0,"mCalorie":0,"mDistance":0,"mWalkStepCount":0,"mNowHealthyStep":0,"mTotalActiveTime":0,"mTimeUnit":600000,"mStepCount":0,"mRunStepCount":0,"mStartTime":0},{"mSpeed":0,"mCalorie":0,"mDistance":0,"mWalkStepCount":0,"mNowHealthyStep":0,"mTotalActiveTime":0,"mTimeUnit":600000,"mStepCount":0,"mRunStepCount":0,"mStartTime":0},{"mSpeed":0,"mCalorie":0,"mDistance":0,"mWalkStepCount":0,"mNowHealthyStep":0,"mTotalActiveTime":0,"mTimeUnit":600000,"mStepCount":0,"mRunStepCount":0,"mStartTime":0},{"mSpeed":0,"mCalorie":0,"mDistance":0,"mWalkStepCount":0,"mNowHealthyStep":0,"mTotalActiveTime":0,"mTimeUnit":600000,"mStepCount":0,"mRunStepCount":0,"mStartTime":0},{"mSpeed":0,"mCalorie":0,"mDistance":0,"mWalkStepCount":0,"mNowHealthyStep":0,"mTotalActiveTime":0,"mTimeUnit":600000,"mStepCount":0,"mRunStepCount":0,"mStartTime":0},{"mSpeed":0,"mCalorie":0,"mDistance":0,"mWalkStepCount":0,"mNowHealthyStep":0,"mTotalActiveTime":0,"mTimeUnit":600000,"mStepCount":0,"mRunStepCount":0,"mStartTime":0},{"mSpeed":0,"mCalorie":0,"mDistance":0,"mWalkStepCount":0,"mNowHealthyStep":0,"mTotalActiveTime":0,"mTimeUnit":600000,"mStepCount":0,"mRunStepCount":0,"mStartTime":0},{"mSpeed":0,"mCalorie":0,"mDistance":0,"mWalkStepCount":0,"mNowHealthyStep":0,"mTotalActiveTime":0,"mTimeUnit":600000,"mStepCount":0,"mRunStepCount":0,"mStartTime":0},{"mSpeed":0,"mCalorie":0,"mDistance":0,"mWalkStepCount":0,"mNowHealthyStep":0,"mTotalActiveTime":0,"mTimeUnit":600000,"mStepCount":0,"mRunStepCount":0,"mStartTime":0},{"mSpeed":0,"mCalorie":0,"mDistance":0,"mWalkStepCount":0,"mNowHealthyStep":0,"mTotalActiveTime":0,"mTimeUnit":600000,"mStepCount":0,"mRunStepCount":0,"mStartTime":0},{"mSpeed":0,"mCalorie":0,"mDistance":0,"mWalkStepCount":0,"mNowHealthyStep":0,"mTotalActiveTime":0,"mTimeUnit":600000,"mStepCount":0,"mRunStepCount":0,"mStartTime":0},{"mSpeed":0,"mCalorie":0,"mDistance":0,"mWalkStepCount":0,"mNowHealthyStep":0,"mTotalActiveTime":0,"mTimeUnit":600000,"mStepCount":0,"mRunStepCount":0,"mStartTime":0},{"mSpeed":0,"mCalorie":0,"mDistance":0,"mWalkStepCount":0,"mNowHealthyStep":0,"mTotalActiveTime":0,"mTimeUnit":600000,"mStepCount":0,"mRunStepCount":0,"mStartTime":0},{"mSpeed":0,"mCalorie":0,"mDistance":0,"mWalkStepCount":0,"mNowHealthyStep":0,"mTotalActiveTime":0,"mTimeUnit":600000,"mStepCount":0,"mRunStepCount":0,"mStartTime":0},{"mSpeed":0,"mCalorie":0,"mDistance":0,"mWalkStepCount":0,"mNowHealthyStep":0,"mTotalActiveTime":0,"mTimeUnit":600000,"mStepCount":0,"mRunStepCount":0,"mStartTime":0},{"mSpeed":0.76442760229110718,"mCalorie":0.51718799999999998,"mDistance":4.2800000000000002,"mWalkStepCount":6,"mNowHealthyStep":0,"mTotalActiveTime":20156.25803388032,"mTimeUnit":600000,"mStepCount":6,"mRunStepCount":0,"mStartTime":0},{"mSpeed":3.443584680557251,"mCalorie":13.979337000000001,"mDistance":268.84917900000005,"mWalkStepCount":392,"mNowHealthyStep":0,"mTotalActiveTime":281060.91463209892,"mTimeUnit":600000,"mStepCount":392,"mRunStepCount":0,"mStartTime":0},{"mSpeed":4.6917929649353027,"mCalorie":3.487495,"mDistance":76.040130000000005,"mWalkStepCount":97,"mNowHealthyStep":0,"mTotalActiveTime":58345.387060909845,"mTimeUnit":600000,"mStepCount":97,"mRunStepCount":0,"mStartTime":0},{"mSpeed":2.3590583801269531,"mCalorie":1.0063850000000001,"mDistance":16.709999,"mWalkStepCount":23,"mNowHealthyStep":0,"mTotalActiveTime":25500.003266880874,"mTimeUnit":600000,"mStepCount":23,"mRunStepCount":0,"mStartTime":0},{"mSpeed":0,"mCalorie":0,"mDistance":0,"mWalkStepCount":0,"mNowHealthyStep":0,"mTotalActiveTime":0,"mTimeUnit":600000,"mStepCount":0,"mRunStepCount":0,"mStartTime":0},{"mSpeed":1.929520845413208,"mCalorie":0.40015400000000001,"mDistance":6.0800000000000001,"mWalkStepCount":13,"mNowHealthyStep":0,"mTotalActiveTime":11343.748916748642,"mTimeUnit":600000,"mStepCount":13,"mRunStepCount":0,"mStartTime":0},{"mSpeed":0,"mCalorie":0,"mDistance":0,"mWalkStepCount":0,"mNowHealthyStep":0,"mTotalActiveTime":0,"mTimeUnit":600000,"mStepCount":0,"mRunStepCount":0,"mStartTime":0},{"mSpeed":3.425114631652832,"mCalorie":24.796744,"mDistance":477.094202,"mWalkStepCount":736,"mNowHealthyStep":0,"mTotalActiveTime":501454.48008163291,"mTimeUnit":600000,"mStepCount":736,"mRunStepCount":0,"mStartTime":0},{"mSpeed":4.879145622253418,"mCalorie":37.288775999999999,"mDistance":812.32274600000005,"mWalkStepCount":1078,"mNowHealthyStep":0,"mTotalActiveTime":599359.41934946214,"mTimeUnit":600000,"mStepCount":1078,"mRunStepCount":0,"mStartTime":0},{"mSpeed":6.1545491218566895,"mCalorie":42.848754999999997,"mDistance":990.85167899999988,"mWalkStepCount":1065,"mNowHealthyStep":0,"mTotalActiveTime":579582.00304672646,"mTimeUnit":600000,"mStepCount":1065,"mRunStepCount":0,"mStartTime":0},{"mSpeed":5.3036847114562988,"mCalorie":35.441732000000002,"mDistance":790.64136800000006,"mWalkStepCount":908,"mNowHealthyStep":0,"mTotalActiveTime":536666.31167603354,"mTimeUnit":600000,"mStepCount":908,"mRunStepCount":0,"mStartTime":0},{"mSpeed":0,"mCalorie":0,"mDistance":0,"mWalkStepCount":0,"mNowHealthyStep":0,"mTotalActiveTime":0,"mTimeUnit":600000,"mStepCount":0,"mRunStepCount":0,"mStartTime":0},{"mSpeed":0,"mCalorie":0,"mDistance":0,"mWalkStepCount":0,"mNowHealthyStep":0,"mTotalActiveTime":0,"mTimeUnit":600000,"mStepCount":0,"mRunStepCount":0,"mStartTime":0},{"mSpeed":0,"mCalorie":0,"mDistance":0,"mWalkStepCount":0,"mNowHealthyStep":0,"mTotalActiveTime":0,"mTimeUnit":600000,"mStepCount":0,"mRunStepCount":0,"mStartTime":0},{"mSpeed":0,"mCalorie":0,"mDistance":0,"mWalkStepCount":0,"mNowHealthyStep":0,"mTotalActiveTime":0,"mTimeUnit":600000,"mStepCount":0,"mRunStepCount":0,"mStartTime":0},{"mSpeed":0,"mCalorie":0,"mDistance":0,"mWalkStepCount":0,"mNowHealthyStep":0,"mTotalActiveTime":0,"mTimeUnit":600000,"mStepCount":0,"mRunStepCount":0,"mStartTime":0},{"mSpeed":2.4590952396392822,"mCalorie":1.4343249999999999,"mDistance":25.210000000000001,"mWalkStepCount":41,"mNowHealthyStep":0,"mTotalActiveTime":36906.257393828215,"mTimeUnit":600000,"mStepCount":41,"mRunStepCount":0,"mStartTime":0},{"mSpeed":0,"mCalorie":0,"mDistance":0,"mWalkStepCount":0,"mNowHealthyStep":0,"mTotalActiveTime":0,"mTimeUnit":600000,"mStepCount":0,"mRunStepCount":0,"mStartTime":0},{"mSpeed":0,"mCalorie":0,"mDistance":0,"mWalkStepCount":0,"mNowHealthyStep":0,"mTotalActiveTime":0,"mTimeUnit":600000,"mStepCount":0,"mRunStepCount":0,"mStartTime":0},{"mSpeed":0,"mCalorie":0,"mDistance":0,"mWalkStepCount":0,"mNowHealthyStep":0,"mTotalActiveTime":0,"mTimeUnit":600000,"mStepCount":0,"mRunStepCount":0,"mStartTime":0},{"mSpeed":0,"mCalorie":0,"mDistance":0,"mWalkStepCount":0,"mNowHealthyStep":0,"mTotalActiveTime":0,"mTimeUnit":600000,"mStepCount":0,"mRunStepCount":0,"mStartTime":0},{"mSpeed":0,"mCalorie":0,"mDistance":0,"mWalkStepCount":0,"mNowHealthyStep":0,"mTotalActiveTime":0,"mTimeUnit":600000,"mStepCount":0,"mRunStepCount":0,"mStartTime":0},{"mSpeed":0,"mCalorie":0,"mDistance":0,"mWalkStepCount":0,"mNowHealthyStep":0,"mTotalActiveTime":0,"mTimeUnit":600000,"mStepCount":0,"mRunStepCount":0,"mStartTime":0},{"mSpeed":0,"mCalorie":0,"mDistance":0,"mWalkStepCount":0,"mNowHealthyStep":0,"mTotalActiveTime":0,"mTimeUnit":600000,"mStepCount":0,"mRunStepCount":0,"mStartTime":0},{"mSpeed":0,"mCalorie":0,"mDistance":0,"mWalkStepCount":0,"mNowHealthyStep":0,"mTotalActiveTime":0,"mTimeUnit":600000,"mStepCount":0,"mRunStepCount":0,"mStartTime":0},{"mSpeed":0,"mCalorie":0,"mDistance":0,"mWalkStepCount":0,"mNowHealthyStep":0,"mTotalActiveTime":0,"mTimeUnit":600000,"mStepCount":0,"mRunStepCount":0,"mStartTime":0},{"mSpeed":0,"mCalorie":0,"mDistance":0,"mWalkStepCount":0,"mNowHealthyStep":0,"mTotalActiveTime":0,"mTimeUnit":600000,"mStepCount":0,"mRunStepCount":0,"mStartTime":0},{"mSpeed":0,"mCalorie":0,"mDistance":0,"mWalkStepCount":0,"mNowHealthyStep":0,"mTotalActiveTime":0,"mTimeUnit":600000,"mStepCount":0,"mRunStepCount":0,"mStartTime":0},{"mSpeed":0,"mCalorie":0,"mDistance":0,"mWalkStepCount":0,"mNowHealthyStep":0,"mTotalActiveTime":0,"mTimeUnit":600000,"mStepCount":0,"mRunStepCount":0,"mStartTime":0},{"mSpeed":0,"mCalorie":0,"mDistance":0,"mWalkStepCount":0,"mNowHealthyStep":0,"mTotalActiveTime":0,"mTimeUnit":600000,"mStepCount":0,"mRunStepCount":0,"mStartTime":0},{"mSpeed":0,"mCalorie":0,"mDistance":0,"mWalkStepCount":0,"mNowHealthyStep":0,"mTotalActiveTime":0,"mTimeUnit":600000,"mStepCount":0,"mRunStepCount":0,"mStartTime":0},{"mSpeed":0,"mCalorie":0,"mDistance":0,"mWalkStepCount":0,"mNowHealthyStep":0,"mTotalActiveTime":0,"mTimeUnit":600000,"mStepCount":0,"mRunStepCount":0,"mStartTime":0},{"mSpeed":0,"mCalorie":0,"mDistance":0,"mWalkStepCount":0,"mNowHealthyStep":0,"mTotalActiveTime":0,"mTimeUnit":600000,"mStepCount":0,"mRunStepCount":0,"mStartTime":0},{"mSpeed":0,"mCalorie":0,"mDistance":0,"mWalkStepCount":0,"mNowHealthyStep":0,"mTotalActiveTime":0,"mTimeUnit":600000,"mStepCount":0,"mRunStepCount":0,"mStartTime":0},{"mSpeed":0,"mCalorie":0,"mDistance":0,"mWalkStepCount":0,"mNowHealthyStep":0,"mTotalActiveTime":0,"mTimeUnit":600000,"mStepCount":0,"mRunStepCount":0,"mStartTime":0},{"mSpeed":0,"mCalorie":0,"mDistance":0,"mWalkStepCount":0,"mNowHealthyStep":0,"mTotalActiveTime":0,"mTimeUnit":600000,"mStepCount":0,"mRunStepCount":0,"mStartTime":0},{"mSpeed":0,"mCalorie":0,"mDistance":0,"mWalkStepCount":0,"mNowHealthyStep":0,"mTotalActiveTime":0,"mTimeUnit":600000,"mStepCount":0,"mRunStepCount":0,"mStartTime":0},{"mSpeed":1.4890561103820801,"mCalorie":2.882943,"mDistance":37.640000000000001,"mWalkStepCount":62,"mNowHealthyStep":0,"mTotalActiveTime":90999.92902540334,"mTimeUnit":600000,"mStepCount":62,"mRunStepCount":0,"mStartTime":0},{"mSpeed":0,"mCalorie":0,"mDistance":0,"mWalkStepCount":0,"mNowHealthyStep":0,"mTotalActiveTime":0,"mTimeUnit":600000,"mStepCount":0,"mRunStepCount":0,"mStartTime":0},{"mSpeed":1.1430068016052246,"mCalorie":0.87413800000000008,"mDistance":9.926438000000001,"mWalkStepCount":16,"mNowHealthyStep":0,"mTotalActiveTime":31264.184124058371,"mTimeUnit":600000,"mStepCount":16,"mRunStepCount":0,"mStartTime":0},{"mSpeed":3.6541943550109863,"mCalorie":0.57142300000000001,"mDistance":11.800000000000001,"mWalkStepCount":17,"mNowHealthyStep":0,"mTotalActiveTime":11624.997433906958,"mTimeUnit":600000,"mStepCount":17,"mRunStepCount":0,"mStartTime":0},{"mSpeed":0,"mCalorie":0,"mDistance":0,"mWalkStepCount":0,"mNowHealthyStep":0,"mTotalActiveTime":0,"mTimeUnit":600000,"mStepCount":0,"mRunStepCount":0,"mStartTime":0},{"mSpeed":0,"mCalorie":0,"mDistance":0,"mWalkStepCount":0,"mNowHealthyStep":0,"mTotalActiveTime":0,"mTimeUnit":600000,"mStepCount":0,"mRunStepCount":0,"mStartTime":0},{"mSpeed":0,"mCalorie":0,"mDistance":0,"mWalkStepCount":0,"mNowHealthyStep":0,"mTotalActiveTime":0,"mTimeUnit":600000,"mStepCount":0,"mRunStepCount":0,"mStartTime":0},{"mSpeed":0,"mCalorie":0,"mDistance":0,"mWalkStepCount":0,"mNowHealthyStep":0,"mTotalActiveTime":0,"mTimeUnit":600000,"mStepCount":0,"mRunStepCount":0,"mStartTime":0},{"mSpeed":0,"mCalorie":0,"mDistance":0,"mWalkStepCount":0,"mNowHealthyStep":0,"mTotalActiveTime":0,"mTimeUnit":600000,"mStepCount":0,"mRunStepCount":0,"mStartTime":0},{"mSpeed":0,"mCalorie":0,"mDistance":0,"mWalkStepCount":0,"mNowHealthyStep":0,"mTotalActiveTime":0,"mTimeUnit":600000,"mStepCount":0,"mRunStepCount":0,"mStartTime":0},{"mSpeed":0,"mCalorie":0,"mDistance":0,"mWalkStepCount":0,"mNowHealthyStep":0,"mTotalActiveTime":0,"mTimeUnit":600000,"mStepCount":0,"mRunStepCount":0,"mStartTime":0},{"mSpeed":0,"mCalorie":0,"mDistance":0,"mWalkStepCount":0,"mNowHealthyStep":0,"mTotalActiveTime":0,"mTimeUnit":600000,"mStepCount":0,"mRunStepCount":0,"mStartTime":0},{"mSpeed":0,"mCalorie":0,"mDistance":0,"mWalkStepCount":0,"mNowHealthyStep":0,"mTotalActiveTime":0,"mTimeUnit":600000,"mStepCount":0,"mRunStepCount":0,"mStartTime":0},{"mSpeed":0,"mCalorie":0,"mDistance":0,"mWalkStepCount":0,"mNowHealthyStep":0,"mTotalActiveTime":0,"mTimeUnit":600000,"mStepCount":0,"mRunStepCount":0,"mStartTime":0},{"mSpeed":0,"mCalorie":0,"mDistance":0,"mWalkStepCount":0,"mNowHealthyStep":0,"mTotalActiveTime":0,"mTimeUnit":600000,"mStepCount":0,"mRunStepCount":0,"mStartTime":0},{"mSpeed":0.56151068210601807,"mCalorie":0.69882299999999997,"mDistance":4.6499989999999993,"mWalkStepCount":5,"mNowHealthyStep":0,"mTotalActiveTime":29812.427290997501,"mTimeUnit":600000,"mStepCount":5,"mRunStepCount":0,"mStartTime":0},{"mSpeed":0,"mCalorie":0,"mDistance":0,"mWalkStepCount":0,"mNowHealthyStep":0,"mTotalActiveTime":0,"mTimeUnit":600000,"mStepCount":0,"mRunStepCount":0,"mStartTime":0},{"mSpeed":1.1041631698608398,"mCalorie":1.3595440000000001,"mDistance":14.44,"mWalkStepCount":26,"mNowHealthyStep":0,"mTotalActiveTime":47079.998155120193,"mTimeUnit":600000,"mStepCount":26,"mRunStepCount":0,"mStartTime":0},{"mSpeed":4.3293390274047852,"mCalorie":31.284180999999997,"mDistance":654.58427400000005,"mWalkStepCount":943,"mNowHealthyStep":0,"mTotalActiveTime":544310.20560996165,"mTimeUnit":600000,"mStepCount":943,"mRunStepCount":0,"mStartTime":0},{"mSpeed":5.0122089385986328,"mCalorie":35.313943000000002,"mDistance":775.34531700000002,"mWalkStepCount":996,"mNowHealthyStep":0,"mTotalActiveTime":556888.82900346827,"mTimeUnit":600000,"mStepCount":996,"mRunStepCount":0,"mStartTime":0},{"mSpeed":4.9462008476257324,"mCalorie":37.847588999999999,"mDistance":824.41039400000011,"mWalkStepCount":1048,"mNowHealthyStep":0,"mTotalActiveTime":600031.72848492407,"mTimeUnit":600000,"mStepCount":1048,"mRunStepCount":0,"mStartTime":0},{"mSpeed":3.8629379272460938,"mCalorie":7.4273220000000002,"mDistance":149.59,"mWalkStepCount":230,"mNowHealthyStep":0,"mTotalActiveTime":139407.88530114407,"mTimeUnit":600000,"mStepCount":230,"mRunStepCount":0,"mStartTime":0},{"mSpeed":0,"mCalorie":0,"mDistance":0,"mWalkStepCount":0,"mNowHealthyStep":0,"mTotalActiveTime":0,"mTimeUnit":600000,"mStepCount":0,"mRunStepCount":0,"mStartTime":0},{"mSpeed":0,"mCalorie":0,"mDistance":0,"mWalkStepCount":0,"mNowHealthyStep":0,"mTotalActiveTime":0,"mTimeUnit":600000,"mStepCount":0,"mRunStepCount":0,"mStartTime":0},{"mSpeed":0,"mCalorie":0,"mDistance":0,"mWalkStepCount":0,"mNowHealthyStep":0,"mTotalActiveTime":0,"mTimeUnit":600000,"mStepCount":0,"mRunStepCount":0,"mStartTime":0},{"mSpeed":4.1221723556518555,"mCalorie":0.51680999999999999,"mDistance":11.199999999999999,"mWalkStepCount":16,"mNowHealthyStep":0,"mTotalActiveTime":9781.2503508337504,"mTimeUnit":600000,"mStepCount":16,"mRunStepCount":0,"mStartTime":0},{"mSpeed":0,"mCalorie":0,"mDistance":0,"mWalkStepCount":0,"mNowHealthyStep":0,"mTotalActiveTime":0,"mTimeUnit":600000,"mStepCount":0,"mRunStepCount":0,"mStartTime":0},{"mSpeed":0,"mCalorie":0,"mDistance":0,"mWalkStepCount":0,"mNowHealthyStep":0,"mTotalActiveTime":0,"mTimeUnit":600000,"mStepCount":0,"mRunStepCount":0,"mStartTime":0},{"mSpeed":1.9127556085586548,"mCalorie":0.28981000000000001,"mDistance":4.4000000000000004,"mWalkStepCount":10,"mNowHealthyStep":0,"mTotalActiveTime":8281.2461399269578,"mTimeUnit":600000,"mStepCount":10,"mRunStepCount":0,"mStartTime":0},{"mSpeed":0,"mCalorie":0,"mDistance":0,"mWalkStepCount":0,"mNowHealthyStep":0,"mTotalActiveTime":0,"mTimeUnit":600000,"mStepCount":0,"mRunStepCount":0,"mStartTime":0},{"mSpeed":0,"mCalorie":0,"mDistance":0,"mWalkStepCount":0,"mNowHealthyStep":0,"mTotalActiveTime":0,"mTimeUnit":600000,"mStepCount":0,"mRunStepCount":0,"mStartTime":0},{"mSpeed":0,"mCalorie":0,"mDistance":0,"mWalkStepCount":0,"mNowHealthyStep":0,"mTotalActiveTime":0,"mTimeUnit":600000,"mStepCount":0,"mRunStepCount":0,"mStartTime":0},{"mSpeed":0,"mCalorie":0,"mDistance":0,"mWalkStepCount":0,"mNowHealthyStep":0,"mTotalActiveTime":0,"mTimeUnit":600000,"mStepCount":0,"mRunStepCount":0,"mStartTime":0},{"mSpeed":0,"mCalorie":0,"mDistance":0,"mWalkStepCount":0,"mNowHealthyStep":0,"mTotalActiveTime":0,"mTimeUnit":600000,"mStepCount":0,"mRunStepCount":0,"mStartTime":0},{"mSpeed":0,"mCalorie":0,"mDistance":0,"mWalkStepCount":0,"mNowHealthyStep":0,"mTotalActiveTime":0,"mTimeUnit":600000,"mStepCount":0,"mRunStepCount":0,"mStartTime":0},{"mSpeed":0,"mCalorie":0,"mDistance":0,"mWalkStepCount":0,"mNowHealthyStep":0,"mTotalActiveTime":0,"mTimeUnit":600000,"mStepCount":0,"mRunStepCount":0,"mStartTime":0},{"mSpeed":0,"mCalorie":0,"mDistance":0,"mWalkStepCount":0,"mNowHealthyStep":0,"mTotalActiveTime":0,"mTimeUnit":600000,"mStepCount":0,"mRunStepCount":0,"mStartTime":0},{"mSpeed":0,"mCalorie":0,"mDistance":0,"mWalkStepCount":0,"mNowHealthyStep":0,"mTotalActiveTime":0,"mTimeUnit":600000,"mStepCount":0,"mRunStepCount":0,"mStartTime":0},{"mSpeed":0,"mCalorie":0,"mDistance":0,"mWalkStepCount":0,"mNowHealthyStep":0,"mTotalActiveTime":0,"mTimeUnit":600000,"mStepCount":0,"mRunStepCount":0,"mStartTime":0},{"mSpeed":0,"mCalorie":0,"mDistance":0,"mWalkStepCount":0,"mNowHealthyStep":0,"mTotalActiveTime":0,"mTimeUnit":600000,"mStepCount":0,"mRunStepCount":0,"mStartTime":0},{"mSpeed":0,"mCalorie":0,"mDistance":0,"mWalkStepCount":0,"mNowHealthyStep":0,"mTotalActiveTime":0,"mTimeUnit":600000,"mStepCount":0,"mRunStepCount":0,"mStartTime":0},{"mSpeed":3.3175063133239746,"mCalorie":10.378917000000001,"mDistance":198.819999,"mWalkStepCount":294,"mNowHealthyStep":0,"mTotalActiveTime":215749.99656714487,"mTimeUnit":600000,"mStepCount":294,"mRunStepCount":0,"mStartTime":0},{"mSpeed":1.6028496026992798,"mCalorie":0.76885499999999996,"mDistance":10.630000000000001,"mWalkStepCount":16,"mNowHealthyStep":0,"mTotalActiveTime":23874.978622794522,"mTimeUnit":600000,"mStepCount":16,"mRunStepCount":0,"mStartTime":0},{"mSpeed":0,"mCalorie":0,"mDistance":0,"mWalkStepCount":0,"mNowHealthyStep":0,"mTotalActiveTime":0,"mTimeUnit":600000,"mStepCount":0,"mRunStepCount":0,"mStartTime":0},{"mSpeed":0,"mCalorie":0,"mDistance":0,"mWalkStepCount":0,"mNowHealthyStep":0,"mTotalActiveTime":0,"mTimeUnit":600000,"mStepCount":0,"mRunStepCount":0,"mStartTime":0},{"mSpeed":3.7404046058654785,"mCalorie":10.468463999999999,"mDistance":208.06000299999999,"mWalkStepCount":276,"mNowHealthyStep":0,"mTotalActiveTime":200249.99856645882,"mTimeUnit":600000,"mStepCount":276,"mRunStepCount":0,"mStartTime":0},{"mSpeed":0,"mCalorie":0,"mDistance":0,"mWalkStepCount":0,"mNowHealthyStep":0,"mTotalActiveTime":0,"mTimeUnit":600000,"mStepCount":0,"mRunStepCount":0,"mStartTime":0},{"mSpeed":2.9503440856933594,"mCalorie":0.77508699999999997,"mDistance":14.470000000000001,"mWalkStepCount":27,"mNowHealthyStep":0,"mTotalActiveTime":17656.245674055976,"mTimeUnit":600000,"mStepCount":27,"mRunStepCount":0,"mStartTime":0},{"mSpeed":0,"mCalorie":0,"mDistance":0,"mWalkStepCount":0,"mNowHealthyStep":0,"mTotalActiveTime":0,"mTimeUnit":600000,"mStepCount":0,"mRunStepCount":0,"mStartTime":0},{"mSpeed":0,"mCalorie":0,"mDistance":0,"mWalkStepCount":0,"mNowHealthyStep":0,"mTotalActiveTime":0,"mTimeUnit":600000,"mStepCount":0,"mRunStepCount":0,"mStartTime":0},{"mSpeed":0,"mCalorie":0,"mDistance":0,"mWalkStepCount":0,"mNowHealthyStep":0,"mTotalActiveTime":0,"mTimeUnit":600000,"mStepCount":0,"mRunStepCount":0,"mStartTime":0},{"mSpeed":0,"mCalorie":0,"mDistance":0,"mWalkStepCount":0,"mNowHealthyStep":0,"mTotalActiveTime":0,"mTimeUnit":600000,"mStepCount":0,"mRunStepCount":0,"mStartTime":0},{"mSpeed":0,"mCalorie":0,"mDistance":0,"mWalkStepCount":0,"mNowHealthyStep":0,"mTotalActiveTime":0,"mTimeUnit":600000,"mStepCount":0,"mRunStepCount":0,"mStartTime":0},{"mSpeed":0,"mCalorie":0,"mDistance":0,"mWalkStepCount":0,"mNowHealthyStep":0,"mTotalActiveTime":0,"mTimeUnit":600000,"mStepCount":0,"mRunStepCount":0,"mStartTime":0},{"mSpeed":0,"mCalorie":0,"mDistance":0,"mWalkStepCount":0,"mNowHealthyStep":0,"mTotalActiveTime":0,"mTimeUnit":600000,"mStepCount":0,"mRunStepCount":0,"mStartTime":0},{"mSpeed":3.4251554012298584,"mCalorie":8.7819279999999988,"mDistance":170.878636,"mWalkStepCount":273,"mNowHealthyStep":0,"mTotalActiveTime":179601.5158370992,"mTimeUnit":600000,"mStepCount":273,"mRunStepCount":0,"mStartTime":0},{"mSpeed":5.2420167922973633,"mCalorie":39.172494,"mDistance":867.47142800000006,"mWalkStepCount":1085,"mNowHealthyStep":0,"mTotalActiveTime":595743.47173760517,"mTimeUnit":600000,"mStepCount":1085,"mRunStepCount":0,"mStartTime":0},{"mSpeed":4.9215664863586426,"mCalorie":36.206547,"mDistance":788.2883979999998,"mWalkStepCount":1006,"mNowHealthyStep":0,"mTotalActiveTime":576612.79959992308,"mTimeUnit":600000,"mStepCount":1006,"mRunStepCount":0,"mStartTime":0},{"mSpeed":4.5395040512084961,"mCalorie":19.054017999999999,"mDistance":405.10152000000005,"mWalkStepCount":531,"mNowHealthyStep":0,"mTotalActiveTime":321260.97217249323,"mTimeUnit":600000,"mStepCount":531,"mRunStepCount":0,"mStartTime":0},{"mSpeed":5.0649166107177734,"mCalorie":11.831925,"mDistance":260.440223,"mWalkStepCount":331,"mNowHealthyStep":0,"mTotalActiveTime":185113.56929283484,"mTimeUnit":600000,"mStepCount":331,"mRunStepCount":0,"mStartTime":0},{"mSpeed":5.3953542709350586,"mCalorie":40.253250000000001,"mDistance":899.37380299999995,"mWalkStepCount":1084,"mNowHealthyStep":0,"mTotalActiveTime":600098.83741877018,"mTimeUnit":600000,"mStepCount":1084,"mRunStepCount":0,"mStartTime":0},{"mSpeed":3.0102365016937256,"mCalorie":7.6580020000000006,"mDistance":140.66596800000002,"mWalkStepCount":213,"mNowHealthyStep":0,"mTotalActiveTime":168225.14558884568,"mTimeUnit":600000,"mStepCount":213,"mRunStepCount":0,"mStartTime":0},{"mSpeed":0,"mCalorie":0,"mDistance":0,"mWalkStepCount":0,"mNowHealthyStep":0,"mTotalActiveTime":0,"mTimeUnit":600000,"mStepCount":0,"mRunStepCount":0,"mStartTime":0},{"mSpeed":0,"mCalorie":0,"mDistance":0,"mWalkStepCount":0,"mNowHealthyStep":0,"mTotalActiveTime":0,"mTimeUnit":600000,"mStepCount":0,"mRunStepCount":0,"mStartTime":0},{"mSpeed":0.51747477054595947,"mCalorie":0.40171000000000001,"mDistance":2.52,"mWalkStepCount":6,"mNowHealthyStep":0,"mTotalActiveTime":17531.289477994505,"mTimeUnit":600000,"mStepCount":6,"mRunStepCount":0,"mStartTime":0},{"mSpeed":0,"mCalorie":0,"mDistance":0,"mWalkStepCount":0,"mNowHealthyStep":0,"mTotalActiveTime":0,"mTimeUnit":600000,"mStepCount":0,"mRunStepCount":0,"mStartTime":0},{"mSpeed":0,"mCalorie":0,"mDistance":0,"mWalkStepCount":0,"mNowHealthyStep":0,"mTotalActiveTime":0,"mTimeUnit":600000,"mStepCount":0,"mRunStepCount":0,"mStartTime":0},{"mSpeed":0,"mCalorie":0,"mDistance":0,"mWalkStepCount":0,"mNowHealthyStep":0,"mTotalActiveTime":0,"mTimeUnit":600000,"mStepCount":0,"mRunStepCount":0,"mStartTime":0},{"mSpeed":0,"mCalorie":0,"mDistance":0,"mWalkStepCount":0,"mNowHealthyStep":0,"mTotalActiveTime":0,"mTimeUnit":600000,"mStepCount":0,"mRunStepCount":0,"mStartTime":0},{"mSpeed":0.73569959402084351,"mCalorie":0.51200199999999996,"mDistance":4.0999999999999996,"mWalkStepCount":5,"mNowHealthyStep":0,"mTotalActiveTime":20062.536556982013,"mTimeUnit":600000,"mStepCount":5,"mRunStepCount":0,"mStartTime":0}]